odoo_mcp/__init__.py
odoo_mcp/__main__.py
odoo_mcp/odoo_client.py
odoo_mcp/server.py
odoo_mcp-0.0.3.dist-info/LICENSE
odoo_mcp-0.0.3.dist-info/METADATA
odoo_mcp-0.0.3.dist-info/WHEEL
odoo_mcp-0.0.3.dist-info/entry_points.txt
odoo_mcp-0.0.3.dist-info/top_level.txt
odoo_mcp-0.0.3.dist-info/RECORD
