Metadata-Version: 2.2
Name: odoo-mcp
Version: 0.0.3
Summary: MCP Server for Odoo Integration
Author-email: Lê Anh Tuấn <justin.le.1105@gmail.com>
License: MIT
Project-URL: Homepage, https://github.com/tuanle96/mcp-odoo
Project-URL: Issues, https://github.com/tuanle96/mcp-odoo/issues
Keywords: odoo,mcp,server
Classifier: License :: OSI Approved :: MIT License
Classifier: Programming Language :: Python :: 3
Classifier: Programming Language :: Python :: 3.10
Classifier: Operating System :: OS Independent
Requires-Python: >=3.10
License-File: LICENSE
Requires-Dist: mcp>=0.1.1
Requires-Dist: requests>=2.31.0
Requires-Dist: xmlrpc>=0.4.1
Provides-Extra: dev
Requires-Dist: black; extra == "dev"
Requires-Dist: isort; extra == "dev"
Requires-Dist: mypy; extra == "dev"
Requires-Dist: ruff; extra == "dev"
Requires-Dist: build; extra == "dev"
Requires-Dist: twine; extra == "dev"
